agent_framework_durabletask/__init__.py
agent_framework_durabletask-0.0.1.dist-info/METADATA
agent_framework_durabletask-0.0.1.dist-info/WHEEL
agent_framework_durabletask-0.0.1.dist-info/top_level.txt
agent_framework_durabletask-0.0.1.dist-info/RECORD
