Metadata-Version: 2.4
Name: agent-framework-durabletask
Version: 0.0.1
Summary: agent-framework-durabletask
Author-email: Gavin Aguiar <gavin.aguiar@microsoft.com>
License-Expression: MIT
Project-URL: Homepage, https://github.com/example/agent-framework-durabletask
Keywords: agent,framework,durable,task
Classifier: Development Status :: 1 - Planning
Classifier: Intended Audience :: Developers
Classifier: Programming Language :: Python :: 3
Classifier: Programming Language :: Python :: 3.10
Classifier: Programming Language :: Python :: 3.11
Classifier: Programming Language :: Python :: 3.12
Requires-Python: >=3.10
